MANIFEST.in
setup.py
ladock/__init__.py
ladock/developerNote.txt
ladock/gmxliglig.py
ladock/gmxprolig.py
ladock/la2vina.py
ladock/ladock4.py
ladock/ladockgpu.py
ladock/lavina.py
ladock/lavinagpu.py
ladock/main.py
ladock.egg-info/PKG-INFO
ladock.egg-info/SOURCES.txt
ladock.egg-info/dependency_links.txt
ladock.egg-info/requires.txt
ladock.egg-info/top_level.txt
ladock/config/gmxligligConfig.py
ladock/config/gmxproligConfig.py
ladock/config/la2vinaConfig.py
ladock/config/ladock4Config.py
ladock/config/ladockgpuConfig.py
ladock/config/lavinaConfig.py
ladock/config/lavinagpuConfig.py
ladock/share/vina_1.2.5_linux_x86_64
ladock/share/vina_split_1.2.5_linux_x86_64
ladock/share/mdp/em.mdp
ladock/share/mdp/ions.mdp
ladock/share/mdp/md.mdp
ladock/share/mdp/npt.mdp
ladock/share/mdp/nvt.mdp