Metadata-Version: 2.1
Name: ladock
Version: 1.0.0
Summary: LADOCK is an innovative and free tool designed for conducting simultaneous simulations in computer-aided drug discovery, encompassing molecular docking and molecular dynamics. In molecular docking, LADOCK excels in handling single or double ligands. It supports ligands from various online sources. In molecular dynamics, LADOCK efficiently manages protein-ligand interactions and even ligand-ligand interactions, accommodating scenarios with one or multiple proteins and ligands.
Author: La Ode Aman
Author-email: laode_aman@ung.ac.id
License: Apache License 2.0
